<?xml version="1.0"?>
<Runs Version="1" Minor="0">
	<Run Id="victor_synth_1" LaunchDir="/afs/athena.mit.edu/user/s/h/shreeyam/Documents/6.111/6111/6111work/Project/sudoku/sudoku.runs/victor_synth_1" FlowId="Vivado_Synthesis" FromStepId="vivado" ToStepId="vivado"/>
	<Run Id="yeung_synth_1" LaunchDir="/afs/athena.mit.edu/user/s/h/shreeyam/Documents/6.111/6111/6111work/Project/sudoku/sudoku.runs/yeung_synth_1" FlowId="Vivado_Synthesis" FromStepId="vivado" ToStepId="vivado"/>
	<Run Id="driss_synth_1" LaunchDir="/afs/athena.mit.edu/user/s/h/shreeyam/Documents/6.111/6111/6111work/Project/sudoku/sudoku.runs/driss_synth_1" FlowId="Vivado_Synthesis" FromStepId="vivado" ToStepId="vivado"/>
	<Run Id="aaron_synth_1" LaunchDir="/afs/athena.mit.edu/user/s/h/shreeyam/Documents/6.111/6111/6111work/Project/sudoku/sudoku.runs/aaron_synth_1" FlowId="Vivado_Synthesis" FromStepId="vivado" ToStepId="vivado"/>
	<Run Id="melinda_synth_1" LaunchDir="/afs/athena.mit.edu/user/s/h/shreeyam/Documents/6.111/6111/6111work/Project/sudoku/sudoku.runs/melinda_synth_1" FlowId="Vivado_Synthesis" FromStepId="vivado" ToStepId="vivado"/>
	<Run Id="blk_mem_gen_0_synth_1" LaunchDir="/afs/athena.mit.edu/user/s/h/shreeyam/Documents/6.111/6111/6111work/Project/sudoku/sudoku.runs/blk_mem_gen_0_synth_1" FlowId="Vivado_Synthesis" FromStepId="vivado" ToStepId="vivado"/>
	<Run Id="mike_synth_1" LaunchDir="/afs/athena.mit.edu/user/s/h/shreeyam/Documents/6.111/6111/6111work/Project/sudoku/sudoku.runs/mike_synth_1" FlowId="Vivado_Synthesis" FromStepId="vivado" ToStepId="vivado"/>
	<Run Id="diana_synth_1" LaunchDir="/afs/athena.mit.edu/user/s/h/shreeyam/Documents/6.111/6111/6111work/Project/sudoku/sudoku.runs/diana_synth_1" FlowId="Vivado_Synthesis" FromStepId="vivado" ToStepId="vivado"/>
	<Run Id="gim_synth_1" LaunchDir="/afs/athena.mit.edu/user/s/h/shreeyam/Documents/6.111/6111/6111work/Project/sudoku/sudoku.runs/gim_synth_1" FlowId="Vivado_Synthesis" FromStepId="vivado" ToStepId="vivado"/>
	<Run Id="synth_1" LaunchDir="/afs/athena.mit.edu/user/s/h/shreeyam/Documents/6.111/6111/6111work/Project/sudoku/sudoku.runs/synth_1" FlowId="Vivado_Synthesis" FromStepId="vivado" ToStepId="vivado">
		<Parent Id="victor_synth_1"/>
		<Parent Id="yeung_synth_1"/>
		<Parent Id="driss_synth_1"/>
		<Parent Id="aaron_synth_1"/>
		<Parent Id="melinda_synth_1"/>
		<Parent Id="blk_mem_gen_0_synth_1"/>
		<Parent Id="mike_synth_1"/>
		<Parent Id="diana_synth_1"/>
		<Parent Id="gim_synth_1"/>
	</Run>
	<Run Id="impl_1" LaunchDir="/afs/athena.mit.edu/user/s/h/shreeyam/Documents/6.111/6111/6111work/Project/sudoku/sudoku.runs/impl_1" FlowId="Vivado_Implementation" FromStepId="init_design" ToStepId="write_bitstream">
		<Parent Id="synth_1"/>
		<Parent Id="victor_synth_1"/>
		<Parent Id="yeung_synth_1"/>
		<Parent Id="driss_synth_1"/>
		<Parent Id="aaron_synth_1"/>
		<Parent Id="melinda_synth_1"/>
		<Parent Id="blk_mem_gen_0_synth_1"/>
		<Parent Id="mike_synth_1"/>
		<Parent Id="diana_synth_1"/>
		<Parent Id="gim_synth_1"/>
	</Run>
</Runs>

